[
  {
    "Keyword": "akar yang yang",
    "Currency": "IDR",
    "Avg_monthly_searches": "",
    "Perubahan_persentase_tiga_bulan": "--",
    "Competition": "Tidak diketahui",
    "Competition_indexed_value": "",
    "Top_of_page_bid_low_range": "",
    "Top_of_page_bid_high_range": "",
    "Ad_impression_share": "",
    "Organic_impression_share": "",
    "Organic_average_position": "",
    "In_account": "",
    "In_plan": "",
    "Searches_Oct_2020": "",
    "Searches_Nov_2020": "",
    "Searches_Dec_2020": "",
    "Searches_Jan_2021": "",
    "Searches_Feb_2021": "",
    "Searches_Mar_2021": "",
    "Searches_Apr_2021": "",
    "Searches_May_2021": "",
    "Searches_Jun_2021": "",
    "Searches_Jul_2021": "",
    "Searches_Aug_2021": "",
    "Searches_Sep_2021": "",
    "Concept_Yang_Lain": "",
    "Concept_Tanaman": "",
    "Concept_Merek_Lain": "",
    "Concept_Non_Merek": ""
  },
  {
    "Keyword": "wortel lobak dan singkong adalah tumbuhan yang berkembang biak dengan",
    "Currency": "IDR",
    "Avg_monthly_searches": 5000,
    "Perubahan_persentase_tiga_bulan": "900%",
    "Competition": "Rendah",
    "Competition_indexed_value": 0,
    "Top_of_page_bid_low_range": "",
    "Top_of_page_bid_high_range": "",
    "Ad_impression_share": "",
    "Organic_impression_share": "",
    "Organic_average_position": "",
    "In_account": "",
    "In_plan": "",
    "Searches_Oct_2020": "",
    "Searches_Nov_2020": "",
    "Searches_Dec_2020": "",
    "Searches_Jan_2021": "",
    "Searches_Feb_2021": "",
    "Searches_Mar_2021": "",
    "Searches_Apr_2021": "",
    "Searches_May_2021": "",
    "Searches_Jun_2021": "",
    "Searches_Jul_2021": "",
    "Searches_Aug_2021": "",
    "Searches_Sep_2021": "",
    "Concept_Yang_Lain": "cara. wortel",
    "Concept_Tanaman": "umbi",
    "Concept_Merek_Lain": "",
    "Concept_Non_Merek": "Non-Brands"
  },
  {
    "Keyword": "tanaman yang berkembang biak dengan rhizoma adalah",
    "Currency": "IDR",
    "Avg_monthly_searches": 5000,
    "Perubahan_persentase_tiga_bulan": "0%",
    "Competition": "Rendah",
    "Competition_indexed_value": 1,
    "Top_of_page_bid_low_range": "",
    "Top_of_page_bid_high_range": "",
    "Ad_impression_share": "",
    "Organic_impression_share": "",
    "Organic_average_position": "",
    "In_account": "",
    "In_plan": "",
    "Searches_Oct_2020": "",
    "Searches_Nov_2020": "",
    "Searches_Dec_2020": "",
    "Searches_Jan_2021": "",
    "Searches_Feb_2021": "",
    "Searches_Mar_2021": "",
    "Searches_Apr_2021": "",
    "Searches_May_2021": "",
    "Searches_Jun_2021": "",
    "Searches_Jul_2021": "",
    "Searches_Aug_2021": "",
    "Searches_Sep_2021": "",
    "Concept_Yang_Lain": "cara",
    "Concept_Tanaman": "",
    "Concept_Merek_Lain": "",
    "Concept_Non_Merek": "Non-Brands"
  },
  {
    "Keyword": "jaringan yang berfungsi mengangkut air dan unsur hara ke daun adalah",
    "Currency": "IDR",
    "Avg_monthly_searches": 5000,
    "Perubahan_persentase_tiga_bulan": "900%",
    "Competition": "Rendah",
    "Competition_indexed_value": 0,
    "Top_of_page_bid_low_range": "",
    "Top_of_page_bid_high_range": "",
    "Ad_impression_share": "",
    "Organic_impression_share": "",
    "Organic_average_position": "",
    "In_account": "",
    "In_plan": "",
    "Searches_Oct_2020": "",
    "Searches_Nov_2020": "",
    "Searches_Dec_2020": "",
    "Searches_Jan_2021": "",
    "Searches_Feb_2021": "",
    "Searches_Mar_2021": "",
    "Searches_Apr_2021": "",
    "Searches_May_2021": "",
    "Searches_Jun_2021": "",
    "Searches_Jul_2021": "",
    "Searches_Aug_2021": "",
    "Searches_Sep_2021": "",
    "Concept_Yang_Lain": "air. jaringan",
    "Concept_Tanaman": "daun",
    "Concept_Merek_Lain": "",
    "Concept_Non_Merek": "Non-Brands"
  },
  {
    "Keyword": "jaringan pembuluh pada tumbuhan yang mengangkut air dan mineral",
    "Currency": "IDR",
    "Avg_monthly_searches": 500,
    "Perubahan_persentase_tiga_bulan": "0%",
    "Competition": "Rendah",
    "Competition_indexed_value": 0,
    "Top_of_page_bid_low_range": "",
    "Top_of_page_bid_high_range": "",
    "Ad_impression_share": "",
    "Organic_impression_share": "",
    "Organic_average_position": "",
    "In_account": "",
    "In_plan": "",
    "Searches_Oct_2020": "",
    "Searches_Nov_2020": "",
    "Searches_Dec_2020": "",
    "Searches_Jan_2021": "",
    "Searches_Feb_2021": "",
    "Searches_Mar_2021": "",
    "Searches_Apr_2021": "",
    "Searches_May_2021": "",
    "Searches_Jun_2021": "",
    "Searches_Jul_2021": "",
    "Searches_Aug_2021": "",
    "Searches_Sep_2021": "",
    "Concept_Yang_Lain": "air. jaringan",
    "Concept_Tanaman": "daun",
    "Concept_Merek_Lain": "",
    "Concept_Non_Merek": "Non-Brands"
  },
  {
    "Keyword": "contoh tumbuhan yang berkembang biak dengan rhizoma",
    "Currency": "IDR",
    "Avg_monthly_searches": 500,
    "Perubahan_persentase_tiga_bulan": "0%",
    "Competition": "Rendah",
    "Competition_indexed_value": 0,
    "Top_of_page_bid_low_range": "",
    "Top_of_page_bid_high_range": "",
    "Ad_impression_share": "",
    "Organic_impression_share": "",
    "Organic_average_position": "",
    "In_account": "",
    "In_plan": "",
    "Searches_Oct_2020": "",
    "Searches_Nov_2020": "",
    "Searches_Dec_2020": "",
    "Searches_Jan_2021": "",
    "Searches_Feb_2021": "",
    "Searches_Mar_2021": "",
    "Searches_Apr_2021": "",
    "Searches_May_2021": "",
    "Searches_Jun_2021": "",
    "Searches_Jul_2021": "",
    "Searches_Aug_2021": "",
    "Searches_Sep_2021": "",
    "Concept_Yang_Lain": "",
    "Concept_Tanaman": "",
    "Concept_Merek_Lain": "",
    "Concept_Non_Merek": "Non-Brands"
  },
  {
    "Keyword": "root vegetables adalah sayuran yang berupa",
    "Currency": "IDR",
    "Avg_monthly_searches": 500,
    "Perubahan_persentase_tiga_bulan": "-90%",
    "Competition": "Rendah",
    "Competition_indexed_value": 0,
    "Top_of_page_bid_low_range": "",
    "Top_of_page_bid_high_range": "",
    "Ad_impression_share": "",
    "Organic_impression_share": "",
    "Organic_average_position": "",
    "In_account": "",
    "In_plan": "",
    "Searches_Oct_2020": "",
    "Searches_Nov_2020": "",
    "Searches_Dec_2020": "",
    "Searches_Jan_2021": "",
    "Searches_Feb_2021": "",
    "Searches_Mar_2021": "",
    "Searches_Apr_2021": "",
    "Searches_May_2021": "",
    "Searches_Jun_2021": "",
    "Searches_Jul_2021": "",
    "Searches_Aug_2021": "",
    "Searches_Sep_2021": "",
    "Concept_Yang_Lain": "tanaman sayuran",
    "Concept_Tanaman": "",
    "Concept_Merek_Lain": "",
    "Concept_Non_Merek": "Non-Brands"
  },
  {
    "Keyword": "bagian dari tanaman yang berfungsi menyerap air dan mineral dari dalam tanah adalah",
    "Currency": "IDR",
    "Avg_monthly_searches": 500,
    "Perubahan_persentase_tiga_bulan": "900%",
    "Competition": "Rendah",
    "Competition_indexed_value": 3,
    "Top_of_page_bid_low_range": "",
    "Top_of_page_bid_high_range": "",
    "Ad_impression_share": "",
    "Organic_impression_share": "",
    "Organic_average_position": "",
    "In_account": "",
    "In_plan": "",
    "Searches_Oct_2020": "",
    "Searches_Nov_2020": "",
    "Searches_Dec_2020": "",
    "Searches_Jan_2021": "",
    "Searches_Feb_2021": "",
    "Searches_Mar_2021": "",
    "Searches_Apr_2021": "",
    "Searches_May_2021": "",
    "Searches_Jun_2021": "",
    "Searches_Jul_2021": "",
    "Searches_Aug_2021": "",
    "Searches_Sep_2021": "",
    "Concept_Yang_Lain": "air",
    "Concept_Tanaman": "",
    "Concept_Merek_Lain": "",
    "Concept_Non_Merek": "Non-Brands"
  },
  {
    "Keyword": "tanaman yang berakar tunggang",
    "Currency": "IDR",
    "Avg_monthly_searches": 500,
    "Perubahan_persentase_tiga_bulan": "900%",
    "Competition": "Rendah",
    "Competition_indexed_value": 1,
    "Top_of_page_bid_low_range": "",
    "Top_of_page_bid_high_range": "",
    "Ad_impression_share": "",
    "Organic_impression_share": "",
    "Organic_average_position": "",
    "In_account": "",
    "In_plan": "",
    "Searches_Oct_2020": "",
    "Searches_Nov_2020": "",
    "Searches_Dec_2020": "",
    "Searches_Jan_2021": "",
    "Searches_Feb_2021": "",
    "Searches_Mar_2021": "",
    "Searches_Apr_2021": "",
    "Searches_May_2021": "",
    "Searches_Jun_2021": "",
    "Searches_Jul_2021": "",
    "Searches_Aug_2021": "",
    "Searches_Sep_2021": "",
    "Concept_Yang_Lain": "",
    "Concept_Tanaman": "",
    "Concept_Merek_Lain": "",
    "Concept_Non_Merek": "Non-Brands"
  },
  {
    "Keyword": "tumbuhan yang berkembang biak dengan rizoma",
    "Currency": "IDR",
    "Avg_monthly_searches": 500,
    "Perubahan_persentase_tiga_bulan": "0%",
    "Competition": "Rendah",
    "Competition_indexed_value": 0,
    "Top_of_page_bid_low_range": "",
    "Top_of_page_bid_high_range": "",
    "Ad_impression_share": "",
    "Organic_impression_share": "",
    "Organic_average_position": "",
    "In_account": "",
    "In_plan": "",
    "Searches_Oct_2020": "",
    "Searches_Nov_2020": "",
    "Searches_Dec_2020": "",
    "Searches_Jan_2021": "",
    "Searches_Feb_2021": "",
    "Searches_Mar_2021": "",
    "Searches_Apr_2021": "",
    "Searches_May_2021": "",
    "Searches_Jun_2021": "",
    "Searches_Jul_2021": "",
    "Searches_Aug_2021": "",
    "Searches_Sep_2021": "",
    "Concept_Yang_Lain": "rizoma",
    "Concept_Tanaman": "",
    "Concept_Merek_Lain": "",
    "Concept_Non_Merek": "Non-Brands"
  },
  {
    "Keyword": "tumbuhan yang berakar serabut",
    "Currency": "IDR",
    "Avg_monthly_searches": 500,
    "Perubahan_persentase_tiga_bulan": "900%",
    "Competition": "Rendah",
    "Competition_indexed_value": 0,
    "Top_of_page_bid_low_range": "",
    "Top_of_page_bid_high_range": "",
    "Ad_impression_share": "",
    "Organic_impression_share": "",
    "Organic_average_position": "",
    "In_account": "",
    "In_plan": "",
    "Searches_Oct_2020": "",
    "Searches_Nov_2020": "",
    "Searches_Dec_2020": "",
    "Searches_Jan_2021": "",
    "Searches_Feb_2021": "",
    "Searches_Mar_2021": "",
    "Searches_Apr_2021": "",
    "Searches_May_2021": "",
    "Searches_Jun_2021": "",
    "Searches_Jul_2021": "",
    "Searches_Aug_2021": "",
    "Searches_Sep_2021": "",
    "Concept_Yang_Lain": "",
    "Concept_Tanaman": "",
    "Concept_Merek_Lain": "",
    "Concept_Non_Merek": "Non-Brands"
  },
  {
    "Keyword": "sayuran yang dimanfaatkan akarnya",
    "Currency": "IDR",
    "Avg_monthly_searches": 500,
    "Perubahan_persentase_tiga_bulan": "0%",
    "Competition": "Rendah",
    "Competition_indexed_value": 0,
    "Top_of_page_bid_low_range": "",
    "Top_of_page_bid_high_range": "",
    "Ad_impression_share": "",
    "Organic_impression_share": "",
    "Organic_average_position": "",
    "In_account": "",
    "In_plan": "",
    "Searches_Oct_2020": "",
    "Searches_Nov_2020": "",
    "Searches_Dec_2020": "",
    "Searches_Jan_2021": "",
    "Searches_Feb_2021": "",
    "Searches_Mar_2021": "",
    "Searches_Apr_2021": "",
    "Searches_May_2021": "",
    "Searches_Jun_2021": "",
    "Searches_Jul_2021": "",
    "Searches_Aug_2021": "",
    "Searches_Sep_2021": "",
    "Concept_Yang_Lain": "tanaman sayuran",
    "Concept_Tanaman": "",
    "Concept_Merek_Lain": "",
    "Concept_Non_Merek": "Non-Brands"
  },
  {
    "Keyword": "cara mengkonsumsi pasak bumi yang benar",
    "Currency": "IDR",
    "Avg_monthly_searches": 500,
    "Perubahan_persentase_tiga_bulan": "0%",
    "Competition": "Rendah",
    "Competition_indexed_value": 25,
    "Top_of_page_bid_low_range": 935.76,
    "Top_of_page_bid_high_range": 3623.85,
    "Ad_impression_share": "",
    "Organic_impression_share": "",
    "Organic_average_position": "",
    "In_account": "",
    "In_plan": "",
    "Searches_Oct_2020": "",
    "Searches_Nov_2020": "",
    "Searches_Dec_2020": "",
    "Searches_Jan_2021": "",
    "Searches_Feb_2021": "",
    "Searches_Mar_2021": "",
    "Searches_Apr_2021": "",
    "Searches_May_2021": "",
    "Searches_Jun_2021": "",
    "Searches_Jul_2021": "",
    "Searches_Aug_2021": "",
    "Searches_Sep_2021": "",
    "Concept_Yang_Lain": "cara",
    "Concept_Tanaman": "",
    "Concept_Merek_Lain": "",
    "Concept_Non_Merek": "Non-Brands"
  },
  {
    "Keyword": "tumbuhan yang berakar tunggang",
    "Currency": "IDR",
    "Avg_monthly_searches": 500,
    "Perubahan_persentase_tiga_bulan": "900%",
    "Competition": "Rendah",
    "Competition_indexed_value": 1,
    "Top_of_page_bid_low_range": "",
    "Top_of_page_bid_high_range": "",
    "Ad_impression_share": "",
    "Organic_impression_share": "",
    "Organic_average_position": "",
    "In_account": "",
    "In_plan": "",
    "Searches_Oct_2020": "",
    "Searches_Nov_2020": "",
    "Searches_Dec_2020": "",
    "Searches_Jan_2021": "",
    "Searches_Feb_2021": "",
    "Searches_Mar_2021": "",
    "Searches_Apr_2021": "",
    "Searches_May_2021": "",
    "Searches_Jun_2021": "",
    "Searches_Jul_2021": "",
    "Searches_Aug_2021": "",
    "Searches_Sep_2021": "",
    "Concept_Yang_Lain": "",
    "Concept_Tanaman": "",
    "Concept_Merek_Lain": "",
    "Concept_Non_Merek": "Non-Brands"
  },
  {
    "Keyword": "wortel lobak dan kentang adalah jenis tanaman yang dimanfaatkan bagian",
    "Currency": "IDR",
    "Avg_monthly_searches": 500,
    "Perubahan_persentase_tiga_bulan": "0%",
    "Competition": "Rendah",
    "Competition_indexed_value": 0,
    "Top_of_page_bid_low_range": "",
    "Top_of_page_bid_high_range": "",
    "Ad_impression_share": "",
    "Organic_impression_share": "",
    "Organic_average_position": "",
    "In_account": "",
    "In_plan": "",
    "Searches_Oct_2020": "",
    "Searches_Nov_2020": "",
    "Searches_Dec_2020": "",
    "Searches_Jan_2021": "",
    "Searches_Feb_2021": "",
    "Searches_Mar_2021": "",
    "Searches_Apr_2021": "",
    "Searches_May_2021": "",
    "Searches_Jun_2021": "",
    "Searches_Jul_2021": "",
    "Searches_Aug_2021": "",
    "Searches_Sep_2021": "",
    "Concept_Yang_Lain": "tanaman sayuran. wortel",
    "Concept_Tanaman": "",
    "Concept_Merek_Lain": "",
    "Concept_Non_Merek": "Non-Brands"
  },
  {
    "Keyword": "harga kayu bajakah yang asli",
    "Currency": "IDR",
    "Avg_monthly_searches": 500,
    "Perubahan_persentase_tiga_bulan": "0%",
    "Competition": "Tinggi",
    "Competition_indexed_value": 79,
    "Top_of_page_bid_low_range": 579.09,
    "Top_of_page_bid_high_range": 2131.03,
    "Ad_impression_share": "",
    "Organic_impression_share": "",
    "Organic_average_position": "",
    "In_account": "",
    "In_plan": "",
    "Searches_Oct_2020": "",
    "Searches_Nov_2020": "",
    "Searches_Dec_2020": "",
    "Searches_Jan_2021": "",
    "Searches_Feb_2021": "",
    "Searches_Mar_2021": "",
    "Searches_Apr_2021": "",
    "Searches_May_2021": "",
    "Searches_Jun_2021": "",
    "Searches_Jul_2021": "",
    "Searches_Aug_2021": "",
    "Searches_Sep_2021": "",
    "Concept_Yang_Lain": "harga",
    "Concept_Tanaman": "",
    "Concept_Merek_Lain": "",
    "Concept_Non_Merek": "Non-Brands"
  },
  {
    "Keyword": "contoh tanaman yang berakar tunggang adalah",
    "Currency": "IDR",
    "Avg_monthly_searches": 500,
    "Perubahan_persentase_tiga_bulan": "900%",
    "Competition": "Rendah",
    "Competition_indexed_value": 1,
    "Top_of_page_bid_low_range": "",
    "Top_of_page_bid_high_range": "",
    "Ad_impression_share": "",
    "Organic_impression_share": "",
    "Organic_average_position": "",
    "In_account": "",
    "In_plan": "",
    "Searches_Oct_2020": "",
    "Searches_Nov_2020": "",
    "Searches_Dec_2020": "",
    "Searches_Jan_2021": "",
    "Searches_Feb_2021": "",
    "Searches_Mar_2021": "",
    "Searches_Apr_2021": "",
    "Searches_May_2021": "",
    "Searches_Jun_2021": "",
    "Searches_Jul_2021": "",
    "Searches_Aug_2021": "",
    "Searches_Sep_2021": "",
    "Concept_Yang_Lain": "",
    "Concept_Tanaman": "",
    "Concept_Merek_Lain": "",
    "Concept_Non_Merek": "Non-Brands"
  },
  {
    "Keyword": "contoh tanaman sayuran yang dimanfaatkan akarnya",
    "Currency": "IDR",
    "Avg_monthly_searches": 500,
    "Perubahan_persentase_tiga_bulan": "0%",
    "Competition": "Rendah",
    "Competition_indexed_value": 0,
    "Top_of_page_bid_low_range": "",
    "Top_of_page_bid_high_range": "",
    "Ad_impression_share": "",
    "Organic_impression_share": "",
    "Organic_average_position": "",
    "In_account": "",
    "In_plan": "",
    "Searches_Oct_2020": "",
    "Searches_Nov_2020": "",
    "Searches_Dec_2020": "",
    "Searches_Jan_2021": "",
    "Searches_Feb_2021": "",
    "Searches_Mar_2021": "",
    "Searches_Apr_2021": "",
    "Searches_May_2021": "",
    "Searches_Jun_2021": "",
    "Searches_Jul_2021": "",
    "Searches_Aug_2021": "",
    "Searches_Sep_2021": "",
    "Concept_Yang_Lain": "tanaman sayuran",
    "Concept_Tanaman": "",
    "Concept_Merek_Lain": "",
    "Concept_Non_Merek": "Non-Brands"
  },
  {
    "Keyword": "contoh tumbuhan yang berakar serabut",
    "Currency": "IDR",
    "Avg_monthly_searches": 500,
    "Perubahan_persentase_tiga_bulan": "900%",
    "Competition": "Rendah",
    "Competition_indexed_value": 0,
    "Top_of_page_bid_low_range": "",
    "Top_of_page_bid_high_range": "",
    "Ad_impression_share": "",
    "Organic_impression_share": "",
    "Organic_average_position": "",
    "In_account": "",
    "In_plan": "",
    "Searches_Oct_2020": "",
    "Searches_Nov_2020": "",
    "Searches_Dec_2020": "",
    "Searches_Jan_2021": "",
    "Searches_Feb_2021": "",
    "Searches_Mar_2021": "",
    "Searches_Apr_2021": "",
    "Searches_May_2021": "",
    "Searches_Jun_2021": "",
    "Searches_Jul_2021": "",
    "Searches_Aug_2021": "",
    "Searches_Sep_2021": "",
    "Concept_Yang_Lain": "",
    "Concept_Tanaman": "",
    "Concept_Merek_Lain": "",
    "Concept_Non_Merek": "Non-Brands"
  },
  {
    "Keyword": "tanaman yang berkembang biak dengan rizoma adalah",
    "Currency": "IDR",
    "Avg_monthly_searches": 500,
    "Perubahan_persentase_tiga_bulan": "0%",
    "Competition": "Rendah",
    "Competition_indexed_value": 1,
    "Top_of_page_bid_low_range": "",
    "Top_of_page_bid_high_range": "",
    "Ad_impression_share": "",
    "Organic_impression_share": "",
    "Organic_average_position": "",
    "In_account": "",
    "In_plan": "",
    "Searches_Oct_2020": "",
    "Searches_Nov_2020": "",
    "Searches_Dec_2020": "",
    "Searches_Jan_2021": "",
    "Searches_Feb_2021": "",
    "Searches_Mar_2021": "",
    "Searches_Apr_2021": "",
    "Searches_May_2021": "",
    "Searches_Jun_2021": "",
    "Searches_Jul_2021": "",
    "Searches_Aug_2021": "",
    "Searches_Sep_2021": "",
    "Concept_Yang_Lain": "cara. rizoma",
    "Concept_Tanaman": "",
    "Concept_Merek_Lain": "",
    "Concept_Non_Merek": "Non-Brands"
  },
  {
    "Keyword": "contoh tanaman yang berkembang biak dengan rhizoma",
    "Currency": "IDR",
    "Avg_monthly_searches": 500,
    "Perubahan_persentase_tiga_bulan": "0%",
    "Competition": "Rendah",
    "Competition_indexed_value": 0,
    "Top_of_page_bid_low_range": "",
    "Top_of_page_bid_high_range": "",
    "Ad_impression_share": "",
    "Organic_impression_share": "",
    "Organic_average_position": "",
    "In_account": "",
    "In_plan": "",
    "Searches_Oct_2020": "",
    "Searches_Nov_2020": "",
    "Searches_Dec_2020": "",
    "Searches_Jan_2021": "",
    "Searches_Feb_2021": "",
    "Searches_Mar_2021": "",
    "Searches_Apr_2021": "",
    "Searches_May_2021": "",
    "Searches_Jun_2021": "",
    "Searches_Jul_2021": "",
    "Searches_Aug_2021": "",
    "Searches_Sep_2021": "",
    "Concept_Yang_Lain": "cara",
    "Concept_Tanaman": "",
    "Concept_Merek_Lain": "",
    "Concept_Non_Merek": "Non-Brands"
  },
  {
    "Keyword": "contoh tumbuhan yang berakar tunggang",
    "Currency": "IDR",
    "Avg_monthly_searches": 500,
    "Perubahan_persentase_tiga_bulan": "900%",
    "Competition": "Rendah",
    "Competition_indexed_value": 0,
    "Top_of_page_bid_low_range": "",
    "Top_of_page_bid_high_range": "",
    "Ad_impression_share": "",
    "Organic_impression_share": "",
    "Organic_average_position": "",
    "In_account": "",
    "In_plan": "",
    "Searches_Oct_2020": "",
    "Searches_Nov_2020": "",
    "Searches_Dec_2020": "",
    "Searches_Jan_2021": "",
    "Searches_Feb_2021": "",
    "Searches_Mar_2021": "",
    "Searches_Apr_2021": "",
    "Searches_May_2021": "",
    "Searches_Jun_2021": "",
    "Searches_Jul_2021": "",
    "Searches_Aug_2021": "",
    "Searches_Sep_2021": "",
    "Concept_Yang_Lain": "",
    "Concept_Tanaman": "",
    "Concept_Merek_Lain": "",
    "Concept_Non_Merek": "Non-Brands"
  },
  {
    "Keyword": "contoh tumbuhan yang berkembang biak dengan rizoma",
    "Currency": "IDR",
    "Avg_monthly_searches": 500,
    "Perubahan_persentase_tiga_bulan": "0%",
    "Competition": "Rendah",
    "Competition_indexed_value": 1,
    "Top_of_page_bid_low_range": "",
    "Top_of_page_bid_high_range": "",
    "Ad_impression_share": "",
    "Organic_impression_share": "",
    "Organic_average_position": "",
    "In_account": "",
    "In_plan": "",
    "Searches_Oct_2020": "",
    "Searches_Nov_2020": "",
    "Searches_Dec_2020": "",
    "Searches_Jan_2021": "",
    "Searches_Feb_2021": "",
    "Searches_Mar_2021": "",
    "Searches_Apr_2021": "",
    "Searches_May_2021": "",
    "Searches_Jun_2021": "",
    "Searches_Jul_2021": "",
    "Searches_Aug_2021": "",
    "Searches_Sep_2021": "",
    "Concept_Yang_Lain": "rizoma",
    "Concept_Tanaman": "",
    "Concept_Merek_Lain": "",
    "Concept_Non_Merek": "Non-Brands"
  },
  {
    "Keyword": "kayu aquascape yang mudah didapat",
    "Currency": "IDR",
    "Avg_monthly_searches": 500,
    "Perubahan_persentase_tiga_bulan": "0%",
    "Competition": "Menengah",
    "Competition_indexed_value": 55,
    "Top_of_page_bid_low_range": "",
    "Top_of_page_bid_high_range": "",
    "Ad_impression_share": "",
    "Organic_impression_share": "",
    "Organic_average_position": "",
    "In_account": "",
    "In_plan": "",
    "Searches_Oct_2020": "",
    "Searches_Nov_2020": "",
    "Searches_Dec_2020": "",
    "Searches_Jan_2021": "",
    "Searches_Feb_2021": "",
    "Searches_Mar_2021": "",
    "Searches_Apr_2021": "",
    "Searches_May_2021": "",
    "Searches_Jun_2021": "",
    "Searches_Jul_2021": "",
    "Searches_Aug_2021": "",
    "Searches_Sep_2021": "",
    "Concept_Yang_Lain": "",
    "Concept_Tanaman": "",
    "Concept_Merek_Lain": "aquascape",
    "Concept_Non_Merek": ""
  },
  {
    "Keyword": "tanaman yang berakar serabut",
    "Currency": "IDR",
    "Avg_monthly_searches": 500,
    "Perubahan_persentase_tiga_bulan": "900%",
    "Competition": "Rendah",
    "Competition_indexed_value": 2,
    "Top_of_page_bid_low_range": "",
    "Top_of_page_bid_high_range": "",
    "Ad_impression_share": "",
    "Organic_impression_share": "",
    "Organic_average_position": "",
    "In_account": "",
    "In_plan": "",
    "Searches_Oct_2020": "",
    "Searches_Nov_2020": "",
    "Searches_Dec_2020": "",
    "Searches_Jan_2021": "",
    "Searches_Feb_2021": "",
    "Searches_Mar_2021": "",
    "Searches_Apr_2021": "",
    "Searches_May_2021": "",
    "Searches_Jun_2021": "",
    "Searches_Jul_2021": "",
    "Searches_Aug_2021": "",
    "Searches_Sep_2021": "",
    "Concept_Yang_Lain": "",
    "Concept_Tanaman": "",
    "Concept_Merek_Lain": "",
    "Concept_Non_Merek": "Non-Brands"
  },
  {
    "Keyword": "cara mengatasi bonggol adenium yang lembek",
    "Currency": "IDR",
    "Avg_monthly_searches": 500,
    "Perubahan_persentase_tiga_bulan": "0%",
    "Competition": "Rendah",
    "Competition_indexed_value": 10,
    "Top_of_page_bid_low_range": "",
    "Top_of_page_bid_high_range": "",
    "Ad_impression_share": "",
    "Organic_impression_share": "",
    "Organic_average_position": "",
    "In_account": "",
    "In_plan": "",
    "Searches_Oct_2020": "",
    "Searches_Nov_2020": "",
    "Searches_Dec_2020": "",
    "Searches_Jan_2021": "",
    "Searches_Feb_2021": "",
    "Searches_Mar_2021": "",
    "Searches_Apr_2021": "",
    "Searches_May_2021": "",
    "Searches_Jun_2021": "",
    "Searches_Jul_2021": "",
    "Searches_Aug_2021": "",
    "Searches_Sep_2021": "",
    "Concept_Yang_Lain": "cara",
    "Concept_Tanaman": "",
    "Concept_Merek_Lain": "",
    "Concept_Non_Merek": "Non-Brands"
  },
  {
    "Keyword": "tanaman yang bisa dimakan akarnya",
    "Currency": "IDR",
    "Avg_monthly_searches": 50,
    "Perubahan_persentase_tiga_bulan": "0%",
    "Competition": "Rendah",
    "Competition_indexed_value": 7,
    "Top_of_page_bid_low_range": "",
    "Top_of_page_bid_high_range": "",
    "Ad_impression_share": "",
    "Organic_impression_share": "",
    "Organic_average_position": "",
    "In_account": "",
    "In_plan": "",
    "Searches_Oct_2020": "",
    "Searches_Nov_2020": "",
    "Searches_Dec_2020": "",
    "Searches_Jan_2021": "",
    "Searches_Feb_2021": "",
    "Searches_Mar_2021": "",
    "Searches_Apr_2021": "",
    "Searches_May_2021": "",
    "Searches_Jun_2021": "",
    "Searches_Jul_2021": "",
    "Searches_Aug_2021": "",
    "Searches_Sep_2021": "",
    "Concept_Yang_Lain": "",
    "Concept_Tanaman": "",
    "Concept_Merek_Lain": "",
    "Concept_Non_Merek": "Non-Brands"
  },
  {
    "Keyword": "bagian tanaman yang berfungsi untuk menyerap air dari tanah adalah",
    "Currency": "IDR",
    "Avg_monthly_searches": 50,
    "Perubahan_persentase_tiga_bulan": "900%",
    "Competition": "Rendah",
    "Competition_indexed_value": 0,
    "Top_of_page_bid_low_range": "",
    "Top_of_page_bid_high_range": "",
    "Ad_impression_share": "",
    "Organic_impression_share": "",
    "Organic_average_position": "",
    "In_account": "",
    "In_plan": "",
    "Searches_Oct_2020": "",
    "Searches_Nov_2020": "",
    "Searches_Dec_2020": "",
    "Searches_Jan_2021": "",
    "Searches_Feb_2021": "",
    "Searches_Mar_2021": "",
    "Searches_Apr_2021": "",
    "Searches_May_2021": "",
    "Searches_Jun_2021": "",
    "Searches_Jul_2021": "",
    "Searches_Aug_2021": "",
    "Searches_Sep_2021": "",
    "Concept_Yang_Lain": "air",
    "Concept_Tanaman": "",
    "Concept_Merek_Lain": "",
    "Concept_Non_Merek": "Non-Brands"
  },
  {
    "Keyword": "bagian tumbuhan yang berfungsi untuk mengangkut air dan mineral dari dalam tanah menuju daun dilakukan oleh jaringan",
    "Currency": "IDR",
    "Avg_monthly_searches": 50,
    "Perubahan_persentase_tiga_bulan": "0%",
    "Competition": "Rendah",
    "Competition_indexed_value": 0,
    "Top_of_page_bid_low_range": "",
    "Top_of_page_bid_high_range": "",
    "Ad_impression_share": "",
    "Organic_impression_share": "",
    "Organic_average_position": "",
    "In_account": "",
    "In_plan": "",
    "Searches_Oct_2020": "",
    "Searches_Nov_2020": "",
    "Searches_Dec_2020": "",
    "Searches_Jan_2021": "",
    "Searches_Feb_2021": "",
    "Searches_Mar_2021": "",
    "Searches_Apr_2021": "",
    "Searches_May_2021": "",
    "Searches_Jun_2021": "",
    "Searches_Jul_2021": "",
    "Searches_Aug_2021": "",
    "Searches_Sep_2021": "",
    "Concept_Yang_Lain": "air. jaringan",
    "Concept_Tanaman": "daun",
    "Concept_Merek_Lain": "",
    "Concept_Non_Merek": "Non-Brands"
  },
  {
    "Keyword": "tanaman sayuran yang dimanfaatkan akarnya",
    "Currency": "IDR",
    "Avg_monthly_searches": 50,
    "Perubahan_persentase_tiga_bulan": "900%",
    "Competition": "Rendah",
    "Competition_indexed_value": 0,
    "Top_of_page_bid_low_range": "",
    "Top_of_page_bid_high_range": "",
    "Ad_impression_share": "",
    "Organic_impression_share": "",
    "Organic_average_position": "",
    "In_account": "",
    "In_plan": "",
    "Searches_Oct_2020": "",
    "Searches_Nov_2020": "",
    "Searches_Dec_2020": "",
    "Searches_Jan_2021": "",
    "Searches_Feb_2021": "",
    "Searches_Mar_2021": "",
    "Searches_Apr_2021": "",
    "Searches_May_2021": "",
    "Searches_Jun_2021": "",
    "Searches_Jul_2021": "",
    "Searches_Aug_2021": "",
    "Searches_Sep_2021": "",
    "Concept_Yang_Lain": "tanaman sayuran",
    "Concept_Tanaman": "",
    "Concept_Merek_Lain": "",
    "Concept_Non_Merek": "Non-Brands"
  },
  {
    "Keyword": "contoh tanaman yang berakar serabut",
    "Currency": "IDR",
    "Avg_monthly_searches": 500,
    "Perubahan_persentase_tiga_bulan": "900%",
    "Competition": "Rendah",
    "Competition_indexed_value": 0,
    "Top_of_page_bid_low_range": "",
    "Top_of_page_bid_high_range": "",
    "Ad_impression_share": "",
    "Organic_impression_share": "",
    "Organic_average_position": "",
    "In_account": "",
    "In_plan": "",
    "Searches_Oct_2020": "",
    "Searches_Nov_2020": "",
    "Searches_Dec_2020": "",
    "Searches_Jan_2021": "",
    "Searches_Feb_2021": "",
    "Searches_Mar_2021": "",
    "Searches_Apr_2021": "",
    "Searches_May_2021": "",
    "Searches_Jun_2021": "",
    "Searches_Jul_2021": "",
    "Searches_Aug_2021": "",
    "Searches_Sep_2021": "",
    "Concept_Yang_Lain": "",
    "Concept_Tanaman": "",
    "Concept_Merek_Lain": "",
    "Concept_Non_Merek": "Non-Brands"
  },
  {
    "Keyword": "tanaman yang dimakan akarnya",
    "Currency": "IDR",
    "Avg_monthly_searches": 50,
    "Perubahan_persentase_tiga_bulan": "0%",
    "Competition": "Rendah",
    "Competition_indexed_value": 9,
    "Top_of_page_bid_low_range": "",
    "Top_of_page_bid_high_range": "",
    "Ad_impression_share": "",
    "Organic_impression_share": "",
    "Organic_average_position": "",
    "In_account": "",
    "In_plan": "",
    "Searches_Oct_2020": "",
    "Searches_Nov_2020": "",
    "Searches_Dec_2020": "",
    "Searches_Jan_2021": "",
    "Searches_Feb_2021": "",
    "Searches_Mar_2021": "",
    "Searches_Apr_2021": "",
    "Searches_May_2021": "",
    "Searches_Jun_2021": "",
    "Searches_Jul_2021": "",
    "Searches_Aug_2021": "",
    "Searches_Sep_2021": "",
    "Concept_Yang_Lain": "",
    "Concept_Tanaman": "",
    "Concept_Merek_Lain": "",
    "Concept_Non_Merek": "Non-Brands"
  },
  {
    "Keyword": "bagian tumbuhan yang berfungsi dalam penyerapan air dan mineral adalah",
    "Currency": "IDR",
    "Avg_monthly_searches": 50,
    "Perubahan_persentase_tiga_bulan": "∞",
    "Competition": "Rendah",
    "Competition_indexed_value": 0,
    "Top_of_page_bid_low_range": "",
    "Top_of_page_bid_high_range": "",
    "Ad_impression_share": "",
    "Organic_impression_share": "",
    "Organic_average_position": "",
    "In_account": "",
    "In_plan": "",
    "Searches_Oct_2020": "",
    "Searches_Nov_2020": "",
    "Searches_Dec_2020": "",
    "Searches_Jan_2021": "",
    "Searches_Feb_2021": "",
    "Searches_Mar_2021": "",
    "Searches_Apr_2021": "",
    "Searches_May_2021": "",
    "Searches_Jun_2021": "",
    "Searches_Jul_2021": "",
    "Searches_Aug_2021": "",
    "Searches_Sep_2021": "",
    "Concept_Yang_Lain": "air",
    "Concept_Tanaman": "daun",
    "Concept_Merek_Lain": "",
    "Concept_Non_Merek": "Non-Brands"
  },
  {
    "Keyword": "tumbuhan yang berakar serabut adalah",
    "Currency": "IDR",
    "Avg_monthly_searches": 50,
    "Perubahan_persentase_tiga_bulan": "900%",
    "Competition": "Rendah",
    "Competition_indexed_value": 0,
    "Top_of_page_bid_low_range": "",
    "Top_of_page_bid_high_range": "",
    "Ad_impression_share": "",
    "Organic_impression_share": "",
    "Organic_average_position": "",
    "In_account": "",
    "In_plan": "",
    "Searches_Oct_2020": "",
    "Searches_Nov_2020": "",
    "Searches_Dec_2020": "",
    "Searches_Jan_2021": "",
    "Searches_Feb_2021": "",
    "Searches_Mar_2021": "",
    "Searches_Apr_2021": "",
    "Searches_May_2021": "",
    "Searches_Jun_2021": "",
    "Searches_Jul_2021": "",
    "Searches_Aug_2021": "",
    "Searches_Sep_2021": "",
    "Concept_Yang_Lain": "",
    "Concept_Tanaman": "",
    "Concept_Merek_Lain": "",
    "Concept_Non_Merek": "Non-Brands"
  },
  {
    "Keyword": "cara merebus bajakah yang benar",
    "Currency": "IDR",
    "Avg_monthly_searches": 50,
    "Perubahan_persentase_tiga_bulan": "0%",
    "Competition": "Rendah",
    "Competition_indexed_value": 5,
    "Top_of_page_bid_low_range": "",
    "Top_of_page_bid_high_range": "",
    "Ad_impression_share": "",
    "Organic_impression_share": "",
    "Organic_average_position": "",
    "In_account": "",
    "In_plan": "",
    "Searches_Oct_2020": "",
    "Searches_Nov_2020": "",
    "Searches_Dec_2020": "",
    "Searches_Jan_2021": "",
    "Searches_Feb_2021": "",
    "Searches_Mar_2021": "",
    "Searches_Apr_2021": "",
    "Searches_May_2021": "",
    "Searches_Jun_2021": "",
    "Searches_Jul_2021": "",
    "Searches_Aug_2021": "",
    "Searches_Sep_2021": "",
    "Concept_Yang_Lain": "cara",
    "Concept_Tanaman": "",
    "Concept_Merek_Lain": "",
    "Concept_Non_Merek": "Non-Brands"
  },
  {
    "Keyword": "jaringan yang berfungsi untuk mengangkut air dan garam mineral adalah",
    "Currency": "IDR",
    "Avg_monthly_searches": 50,
    "Perubahan_persentase_tiga_bulan": "0%",
    "Competition": "Rendah",
    "Competition_indexed_value": 0,
    "Top_of_page_bid_low_range": "",
    "Top_of_page_bid_high_range": "",
    "Ad_impression_share": "",
    "Organic_impression_share": "",
    "Organic_average_position": "",
    "In_account": "",
    "In_plan": "",
    "Searches_Oct_2020": "",
    "Searches_Nov_2020": "",
    "Searches_Dec_2020": "",
    "Searches_Jan_2021": "",
    "Searches_Feb_2021": "",
    "Searches_Mar_2021": "",
    "Searches_Apr_2021": "",
    "Searches_May_2021": "",
    "Searches_Jun_2021": "",
    "Searches_Jul_2021": "",
    "Searches_Aug_2021": "",
    "Searches_Sep_2021": "",
    "Concept_Yang_Lain": "air. jaringan",
    "Concept_Tanaman": "daun",
    "Concept_Merek_Lain": "",
    "Concept_Non_Merek": "Non-Brands"
  },
  {
    "Keyword": "bagian kunyit yang mendukung tumbuhnya perakaran baru adalah",
    "Currency": "IDR",
    "Avg_monthly_searches": 50,
    "Perubahan_persentase_tiga_bulan": "900%",
    "Competition": "Rendah",
    "Competition_indexed_value": 0,
    "Top_of_page_bid_low_range": "",
    "Top_of_page_bid_high_range": "",
    "Ad_impression_share": "",
    "Organic_impression_share": "",
    "Organic_average_position": "",
    "In_account": "",
    "In_plan": "",
    "Searches_Oct_2020": "",
    "Searches_Nov_2020": "",
    "Searches_Dec_2020": "",
    "Searches_Jan_2021": "",
    "Searches_Feb_2021": "",
    "Searches_Mar_2021": "",
    "Searches_Apr_2021": "",
    "Searches_May_2021": "",
    "Searches_Jun_2021": "",
    "Searches_Jul_2021": "",
    "Searches_Aug_2021": "",
    "Searches_Sep_2021": "",
    "Concept_Yang_Lain": "",
    "Concept_Tanaman": "",
    "Concept_Merek_Lain": "",
    "Concept_Non_Merek": "Non-Brands"
  },
  {
    "Keyword": "tanaman yang berkembang biak dengan rizoma",
    "Currency": "IDR",
    "Avg_monthly_searches": 500,
    "Perubahan_persentase_tiga_bulan": "0%",
    "Competition": "Rendah",
    "Competition_indexed_value": 3,
    "Top_of_page_bid_low_range": "",
    "Top_of_page_bid_high_range": "",
    "Ad_impression_share": "",
    "Organic_impression_share": "",
    "Organic_average_position": "",
    "In_account": "",
    "In_plan": "",
    "Searches_Oct_2020": "",
    "Searches_Nov_2020": "",
    "Searches_Dec_2020": "",
    "Searches_Jan_2021": "",
    "Searches_Feb_2021": "",
    "Searches_Mar_2021": "",
    "Searches_Apr_2021": "",
    "Searches_May_2021": "",
    "Searches_Jun_2021": "",
    "Searches_Jul_2021": "",
    "Searches_Aug_2021": "",
    "Searches_Sep_2021": "",
    "Concept_Yang_Lain": "cara. rizoma",
    "Concept_Tanaman": "",
    "Concept_Merek_Lain": "",
    "Concept_Non_Merek": "Non-Brands"
  },
  {
    "Keyword": "tumbuhan yang berakar tunggal",
    "Currency": "IDR",
    "Avg_monthly_searches": 50,
    "Perubahan_persentase_tiga_bulan": "900%",
    "Competition": "Rendah",
    "Competition_indexed_value": 0,
    "Top_of_page_bid_low_range": "",
    "Top_of_page_bid_high_range": "",
    "Ad_impression_share": "",
    "Organic_impression_share": "",
    "Organic_average_position": "",
    "In_account": "",
    "In_plan": "",
    "Searches_Oct_2020": "",
    "Searches_Nov_2020": "",
    "Searches_Dec_2020": "",
    "Searches_Jan_2021": "",
    "Searches_Feb_2021": "",
    "Searches_Mar_2021": "",
    "Searches_Apr_2021": "",
    "Searches_May_2021": "",
    "Searches_Jun_2021": "",
    "Searches_Jul_2021": "",
    "Searches_Aug_2021": "",
    "Searches_Sep_2021": "",
    "Concept_Yang_Lain": "",
    "Concept_Tanaman": "",
    "Concept_Merek_Lain": "",
    "Concept_Non_Merek": "Non-Brands"
  },
  {
    "Keyword": "sebutkan jaringan yang menyusun organ batang tumbuhan",
    "Currency": "IDR",
    "Avg_monthly_searches": 50,
    "Perubahan_persentase_tiga_bulan": "∞",
    "Competition": "Rendah",
    "Competition_indexed_value": 0,
    "Top_of_page_bid_low_range": "",
    "Top_of_page_bid_high_range": "",
    "Ad_impression_share": "",
    "Organic_impression_share": "",
    "Organic_average_position": "",
    "In_account": "",
    "In_plan": "",
    "Searches_Oct_2020": "",
    "Searches_Nov_2020": "",
    "Searches_Dec_2020": "",
    "Searches_Jan_2021": "",
    "Searches_Feb_2021": "",
    "Searches_Mar_2021": "",
    "Searches_Apr_2021": "",
    "Searches_May_2021": "",
    "Searches_Jun_2021": "",
    "Searches_Jul_2021": "",
    "Searches_Aug_2021": "",
    "Searches_Sep_2021": "",
    "Concept_Yang_Lain": "jaringan",
    "Concept_Tanaman": "batang",
    "Concept_Merek_Lain": "",
    "Concept_Non_Merek": "Non-Brands"
  },
  {
    "Keyword": "kayu bajakah yang asli",
    "Currency": "IDR",
    "Avg_monthly_searches": 500,
    "Perubahan_persentase_tiga_bulan": "0%",
    "Competition": "Tinggi",
    "Competition_indexed_value": 99,
    "Top_of_page_bid_low_range": 561.86,
    "Top_of_page_bid_high_range": 1971.44,
    "Ad_impression_share": "",
    "Organic_impression_share": "",
    "Organic_average_position": "",
    "In_account": "",
    "In_plan": "",
    "Searches_Oct_2020": "",
    "Searches_Nov_2020": "",
    "Searches_Dec_2020": "",
    "Searches_Jan_2021": "",
    "Searches_Feb_2021": "",
    "Searches_Mar_2021": "",
    "Searches_Apr_2021": "",
    "Searches_May_2021": "",
    "Searches_Jun_2021": "",
    "Searches_Jul_2021": "",
    "Searches_Aug_2021": "",
    "Searches_Sep_2021": "",
    "Concept_Yang_Lain": "",
    "Concept_Tanaman": "",
    "Concept_Merek_Lain": "",
    "Concept_Non_Merek": "Non-Brands"
  },
  {
    "Keyword": "kayu yang bagus untuk aquascape",
    "Currency": "IDR",
    "Avg_monthly_searches": 500,
    "Perubahan_persentase_tiga_bulan": "0%",
    "Competition": "Tinggi",
    "Competition_indexed_value": 86,
    "Top_of_page_bid_low_range": "",
    "Top_of_page_bid_high_range": "",
    "Ad_impression_share": "",
    "Organic_impression_share": "",
    "Organic_average_position": "",
    "In_account": "",
    "In_plan": "",
    "Searches_Oct_2020": "",
    "Searches_Nov_2020": "",
    "Searches_Dec_2020": "",
    "Searches_Jan_2021": "",
    "Searches_Feb_2021": "",
    "Searches_Mar_2021": "",
    "Searches_Apr_2021": "",
    "Searches_May_2021": "",
    "Searches_Jun_2021": "",
    "Searches_Jul_2021": "",
    "Searches_Aug_2021": "",
    "Searches_Sep_2021": "",
    "Concept_Yang_Lain": "",
    "Concept_Tanaman": "",
    "Concept_Merek_Lain": "aquascape",
    "Concept_Non_Merek": ""
  },
  {
    "Keyword": "jenis kayu aquascape yang mudah didapat",
    "Currency": "IDR",
    "Avg_monthly_searches": 50,
    "Perubahan_persentase_tiga_bulan": "0%",
    "Competition": "Tinggi",
    "Competition_indexed_value": 88,
    "Top_of_page_bid_low_range": "",
    "Top_of_page_bid_high_range": "",
    "Ad_impression_share": "",
    "Organic_impression_share": "",
    "Organic_average_position": "",
    "In_account": "",
    "In_plan": "",
    "Searches_Oct_2020": "",
    "Searches_Nov_2020": "",
    "Searches_Dec_2020": "",
    "Searches_Jan_2021": "",
    "Searches_Feb_2021": "",
    "Searches_Mar_2021": "",
    "Searches_Apr_2021": "",
    "Searches_May_2021": "",
    "Searches_Jun_2021": "",
    "Searches_Jul_2021": "",
    "Searches_Aug_2021": "",
    "Searches_Sep_2021": "",
    "Concept_Yang_Lain": "",
    "Concept_Tanaman": "",
    "Concept_Merek_Lain": "aquascape",
    "Concept_Non_Merek": ""
  },
  {
    "Keyword": "cara merebus kayu bajakah yang benar",
    "Currency": "IDR",
    "Avg_monthly_searches": 50,
    "Perubahan_persentase_tiga_bulan": "0%",
    "Competition": "Menengah",
    "Competition_indexed_value": 36,
    "Top_of_page_bid_low_range": "",
    "Top_of_page_bid_high_range": "",
    "Ad_impression_share": "",
    "Organic_impression_share": "",
    "Organic_average_position": "",
    "In_account": "",
    "In_plan": "",
    "Searches_Oct_2020": "",
    "Searches_Nov_2020": "",
    "Searches_Dec_2020": "",
    "Searches_Jan_2021": "",
    "Searches_Feb_2021": "",
    "Searches_Mar_2021": "",
    "Searches_Apr_2021": "",
    "Searches_May_2021": "",
    "Searches_Jun_2021": "",
    "Searches_Jul_2021": "",
    "Searches_Aug_2021": "",
    "Searches_Sep_2021": "",
    "Concept_Yang_Lain": "cara",
    "Concept_Tanaman": "",
    "Concept_Merek_Lain": "",
    "Concept_Non_Merek": "Non-Brands"
  },
  {
    "Keyword": "tanaman yang akarnya tidak merusak bangunan",
    "Currency": "IDR",
    "Avg_monthly_searches": 50,
    "Perubahan_persentase_tiga_bulan": "0%",
    "Competition": "Tinggi",
    "Competition_indexed_value": 84,
    "Top_of_page_bid_low_range": "",
    "Top_of_page_bid_high_range": "",
    "Ad_impression_share": "",
    "Organic_impression_share": "",
    "Organic_average_position": "",
    "In_account": "",
    "In_plan": "",
    "Searches_Oct_2020": "",
    "Searches_Nov_2020": "",
    "Searches_Dec_2020": "",
    "Searches_Jan_2021": "",
    "Searches_Feb_2021": "",
    "Searches_Mar_2021": "",
    "Searches_Apr_2021": "",
    "Searches_May_2021": "",
    "Searches_Jun_2021": "",
    "Searches_Jul_2021": "",
    "Searches_Aug_2021": "",
    "Searches_Sep_2021": "",
    "Concept_Yang_Lain": "",
    "Concept_Tanaman": "",
    "Concept_Merek_Lain": "",
    "Concept_Non_Merek": "Non-Brands"
  },
  {
    "Keyword": "cara mengobati sakit gigi yang tinggal akarnya",
    "Currency": "IDR",
    "Avg_monthly_searches": 50,
    "Perubahan_persentase_tiga_bulan": "0%",
    "Competition": "Menengah",
    "Competition_indexed_value": 57,
    "Top_of_page_bid_low_range": "",
    "Top_of_page_bid_high_range": "",
    "Ad_impression_share": "",
    "Organic_impression_share": "",
    "Organic_average_position": "",
    "In_account": "",
    "In_plan": "",
    "Searches_Oct_2020": "",
    "Searches_Nov_2020": "",
    "Searches_Dec_2020": "",
    "Searches_Jan_2021": "",
    "Searches_Feb_2021": "",
    "Searches_Mar_2021": "",
    "Searches_Apr_2021": "",
    "Searches_May_2021": "",
    "Searches_Jun_2021": "",
    "Searches_Jul_2021": "",
    "Searches_Aug_2021": "",
    "Searches_Sep_2021": "",
    "Concept_Yang_Lain": "cara",
    "Concept_Tanaman": "",
    "Concept_Merek_Lain": "",
    "Concept_Non_Merek": "Non-Brands"
  },
  {
    "Keyword": "bagian yang berfungsi mengedarkan mineral dan air adalah",
    "Currency": "IDR",
    "Avg_monthly_searches": 50,
    "Perubahan_persentase_tiga_bulan": "∞",
    "Competition": "Rendah",
    "Competition_indexed_value": 0,
    "Top_of_page_bid_low_range": "",
    "Top_of_page_bid_high_range": "",
    "Ad_impression_share": "",
    "Organic_impression_share": "",
    "Organic_average_position": "",
    "In_account": "",
    "In_plan": "",
    "Searches_Oct_2020": "",
    "Searches_Nov_2020": "",
    "Searches_Dec_2020": "",
    "Searches_Jan_2021": "",
    "Searches_Feb_2021": "",
    "Searches_Mar_2021": "",
    "Searches_Apr_2021": "",
    "Searches_May_2021": "",
    "Searches_Jun_2021": "",
    "Searches_Jul_2021": "",
    "Searches_Aug_2021": "",
    "Searches_Sep_2021": "",
    "Concept_Yang_Lain": "air",
    "Concept_Tanaman": "",
    "Concept_Merek_Lain": "",
    "Concept_Non_Merek": "Non-Brands"
  },
  {
    "Keyword": "contoh tanaman yang berkembang biak dengan rizoma",
    "Currency": "IDR",
    "Avg_monthly_searches": 50,
    "Perubahan_persentase_tiga_bulan": "0%",
    "Competition": "Rendah",
    "Competition_indexed_value": 0,
    "Top_of_page_bid_low_range": "",
    "Top_of_page_bid_high_range": "",
    "Ad_impression_share": "",
    "Organic_impression_share": "",
    "Organic_average_position": "",
    "In_account": "",
    "In_plan": "",
    "Searches_Oct_2020": "",
    "Searches_Nov_2020": "",
    "Searches_Dec_2020": "",
    "Searches_Jan_2021": "",
    "Searches_Feb_2021": "",
    "Searches_Mar_2021": "",
    "Searches_Apr_2021": "",
    "Searches_May_2021": "",
    "Searches_Jun_2021": "",
    "Searches_Jul_2021": "",
    "Searches_Aug_2021": "",
    "Searches_Sep_2021": "",
    "Concept_Yang_Lain": "cara. rizoma",
    "Concept_Tanaman": "",
    "Concept_Merek_Lain": "",
    "Concept_Non_Merek": "Non-Brands"
  },
  {
    "Keyword": "umbi korang",
    "Currency": "IDR",
    "Avg_monthly_searches": 50,
    "Perubahan_persentase_tiga_bulan": "0%",
    "Competition": "Rendah",
    "Competition_indexed_value": 22,
    "Top_of_page_bid_low_range": "",
    "Top_of_page_bid_high_range": "",
    "Ad_impression_share": "",
    "Organic_impression_share": "",
    "Organic_average_position": "",
    "In_account": "",
    "In_plan": "",
    "Searches_Oct_2020": "",
    "Searches_Nov_2020": "",
    "Searches_Dec_2020": "",
    "Searches_Jan_2021": "",
    "Searches_Feb_2021": "",
    "Searches_Mar_2021": "",
    "Searches_Apr_2021": "",
    "Searches_May_2021": "",
    "Searches_Jun_2021": "",
    "Searches_Jul_2021": "",
    "Searches_Aug_2021": "",
    "Searches_Sep_2021": "",
    "Concept_Yang_Lain": "",
    "Concept_Tanaman": "umbi",
    "Concept_Merek_Lain": "",
    "Concept_Non_Merek": "Non-Brands"
  },
  {
    "Keyword": "cara mencabut gigi yang tinggal akarnya",
    "Currency": "IDR",
    "Avg_monthly_searches": 50,
    "Perubahan_persentase_tiga_bulan": "0%",
    "Competition": "Rendah",
    "Competition_indexed_value": 31,
    "Top_of_page_bid_low_range": "",
    "Top_of_page_bid_high_range": "",
    "Ad_impression_share": "",
    "Organic_impression_share": "",
    "Organic_average_position": "",
    "In_account": "",
    "In_plan": "",
    "Searches_Oct_2020": "",
    "Searches_Nov_2020": "",
    "Searches_Dec_2020": "",
    "Searches_Jan_2021": "",
    "Searches_Feb_2021": "",
    "Searches_Mar_2021": "",
    "Searches_Apr_2021": "",
    "Searches_May_2021": "",
    "Searches_Jun_2021": "",
    "Searches_Jul_2021": "",
    "Searches_Aug_2021": "",
    "Searches_Sep_2021": "",
    "Concept_Yang_Lain": "cara",
    "Concept_Tanaman": "",
    "Concept_Merek_Lain": "",
    "Concept_Non_Merek": "Non-Brands"
  },
  {
    "Keyword": "cara mengatasi sakit gigi yang tinggal akarnya",
    "Currency": "IDR",
    "Avg_monthly_searches": 50,
    "Perubahan_persentase_tiga_bulan": "0%",
    "Competition": "Rendah",
    "Competition_indexed_value": 14,
    "Top_of_page_bid_low_range": "",
    "Top_of_page_bid_high_range": "",
    "Ad_impression_share": "",
    "Organic_impression_share": "",
    "Organic_average_position": "",
    "In_account": "",
    "In_plan": "",
    "Searches_Oct_2020": "",
    "Searches_Nov_2020": "",
    "Searches_Dec_2020": "",
    "Searches_Jan_2021": "",
    "Searches_Feb_2021": "",
    "Searches_Mar_2021": "",
    "Searches_Apr_2021": "",
    "Searches_May_2021": "",
    "Searches_Jun_2021": "",
    "Searches_Jul_2021": "",
    "Searches_Aug_2021": "",
    "Searches_Sep_2021": "",
    "Concept_Yang_Lain": "cara",
    "Concept_Tanaman": "",
    "Concept_Merek_Lain": "",
    "Concept_Non_Merek": "Non-Brands"
  },
  {
    "Keyword": "contoh tanaman yang berkembang biak dengan rizoma adalah",
    "Currency": "IDR",
    "Avg_monthly_searches": 50,
    "Perubahan_persentase_tiga_bulan": "0%",
    "Competition": "Rendah",
    "Competition_indexed_value": 0,
    "Top_of_page_bid_low_range": "",
    "Top_of_page_bid_high_range": "",
    "Ad_impression_share": "",
    "Organic_impression_share": "",
    "Organic_average_position": "",
    "In_account": "",
    "In_plan": "",
    "Searches_Oct_2020": "",
    "Searches_Nov_2020": "",
    "Searches_Dec_2020": "",
    "Searches_Jan_2021": "",
    "Searches_Feb_2021": "",
    "Searches_Mar_2021": "",
    "Searches_Apr_2021": "",
    "Searches_May_2021": "",
    "Searches_Jun_2021": "",
    "Searches_Jul_2021": "",
    "Searches_Aug_2021": "",
    "Searches_Sep_2021": "",
    "Concept_Yang_Lain": "cara. rizoma",
    "Concept_Tanaman": "",
    "Concept_Merek_Lain": "",
    "Concept_Non_Merek": "Non-Brands"
  },
  {
    "Keyword": "tema realme yang tembus aplikasi",
    "Currency": "IDR",
    "Avg_monthly_searches": 50,
    "Perubahan_persentase_tiga_bulan": "0%",
    "Competition": "Rendah",
    "Competition_indexed_value": 0,
    "Top_of_page_bid_low_range": "",
    "Top_of_page_bid_high_range": "",
    "Ad_impression_share": "",
    "Organic_impression_share": "",
    "Organic_average_position": "",
    "In_account": "",
    "In_plan": "",
    "Searches_Oct_2020": "",
    "Searches_Nov_2020": "",
    "Searches_Dec_2020": "",
    "Searches_Jan_2021": "",
    "Searches_Feb_2021": "",
    "Searches_Mar_2021": "",
    "Searches_Apr_2021": "",
    "Searches_May_2021": "",
    "Searches_Jun_2021": "",
    "Searches_Jul_2021": "",
    "Searches_Aug_2021": "",
    "Searches_Sep_2021": "",
    "Concept_Yang_Lain": "cara",
    "Concept_Tanaman": "",
    "Concept_Merek_Lain": "realme",
    "Concept_Non_Merek": ""
  },
  {
    "Keyword": "cara mengatasi gigi yang tinggal akarnya",
    "Currency": "IDR",
    "Avg_monthly_searches": 50,
    "Perubahan_persentase_tiga_bulan": "0%",
    "Competition": "Menengah",
    "Competition_indexed_value": 39,
    "Top_of_page_bid_low_range": "",
    "Top_of_page_bid_high_range": "",
    "Ad_impression_share": "",
    "Organic_impression_share": "",
    "Organic_average_position": "",
    "In_account": "",
    "In_plan": "",
    "Searches_Oct_2020": "",
    "Searches_Nov_2020": "",
    "Searches_Dec_2020": "",
    "Searches_Jan_2021": "",
    "Searches_Feb_2021": "",
    "Searches_Mar_2021": "",
    "Searches_Apr_2021": "",
    "Searches_May_2021": "",
    "Searches_Jun_2021": "",
    "Searches_Jul_2021": "",
    "Searches_Aug_2021": "",
    "Searches_Sep_2021": "",
    "Concept_Yang_Lain": "cara",
    "Concept_Tanaman": "",
    "Concept_Merek_Lain": "",
    "Concept_Non_Merek": "Non-Brands"
  },
  {
    "Keyword": "tanaman yang akarnya di air",
    "Currency": "IDR",
    "Avg_monthly_searches": 50,
    "Perubahan_persentase_tiga_bulan": "0%",
    "Competition": "Tinggi",
    "Competition_indexed_value": 78,
    "Top_of_page_bid_low_range": "",
    "Top_of_page_bid_high_range": "",
    "Ad_impression_share": "",
    "Organic_impression_share": "",
    "Organic_average_position": "",
    "In_account": "",
    "In_plan": "",
    "Searches_Oct_2020": "",
    "Searches_Nov_2020": "",
    "Searches_Dec_2020": "",
    "Searches_Jan_2021": "",
    "Searches_Feb_2021": "",
    "Searches_Mar_2021": "",
    "Searches_Apr_2021": "",
    "Searches_May_2021": "",
    "Searches_Jun_2021": "",
    "Searches_Jul_2021": "",
    "Searches_Aug_2021": "",
    "Searches_Sep_2021": "",
    "Concept_Yang_Lain": "air",
    "Concept_Tanaman": "",
    "Concept_Merek_Lain": "",
    "Concept_Non_Merek": "Non-Brands"
  },
  {
    "Keyword": "bajakah yang asli",
    "Currency": "IDR",
    "Avg_monthly_searches": 50,
    "Perubahan_persentase_tiga_bulan": "0%",
    "Competition": "Tinggi",
    "Competition_indexed_value": 100,
    "Top_of_page_bid_low_range": 569.87,
    "Top_of_page_bid_high_range": 2082.58,
    "Ad_impression_share": "",
    "Organic_impression_share": "",
    "Organic_average_position": "",
    "In_account": "",
    "In_plan": "",
    "Searches_Oct_2020": "",
    "Searches_Nov_2020": "",
    "Searches_Dec_2020": "",
    "Searches_Jan_2021": "",
    "Searches_Feb_2021": "",
    "Searches_Mar_2021": "",
    "Searches_Apr_2021": "",
    "Searches_May_2021": "",
    "Searches_Jun_2021": "",
    "Searches_Jul_2021": "",
    "Searches_Aug_2021": "",
    "Searches_Sep_2021": "",
    "Concept_Yang_Lain": "",
    "Concept_Tanaman": "",
    "Concept_Merek_Lain": "",
    "Concept_Non_Merek": "Non-Brands"
  },
  {
    "Keyword": "tumbuhan yang menyerap air",
    "Currency": "IDR",
    "Avg_monthly_searches": 50,
    "Perubahan_persentase_tiga_bulan": "0%",
    "Competition": "Rendah",
    "Competition_indexed_value": 0,
    "Top_of_page_bid_low_range": "",
    "Top_of_page_bid_high_range": "",
    "Ad_impression_share": "",
    "Organic_impression_share": "",
    "Organic_average_position": "",
    "In_account": "",
    "In_plan": "",
    "Searches_Oct_2020": "",
    "Searches_Nov_2020": "",
    "Searches_Dec_2020": "",
    "Searches_Jan_2021": "",
    "Searches_Feb_2021": "",
    "Searches_Mar_2021": "",
    "Searches_Apr_2021": "",
    "Searches_May_2021": "",
    "Searches_Jun_2021": "",
    "Searches_Jul_2021": "",
    "Searches_Aug_2021": "",
    "Searches_Sep_2021": "",
    "Concept_Yang_Lain": "air",
    "Concept_Tanaman": "",
    "Concept_Merek_Lain": "",
    "Concept_Non_Merek": "Non-Brands"
  },
  {
    "Keyword": "tanaman peneduh yang akarnya tidak merusak",
    "Currency": "IDR",
    "Avg_monthly_searches": 50,
    "Perubahan_persentase_tiga_bulan": "0%",
    "Competition": "Tinggi",
    "Competition_indexed_value": 89,
    "Top_of_page_bid_low_range": "",
    "Top_of_page_bid_high_range": "",
    "Ad_impression_share": "",
    "Organic_impression_share": "",
    "Organic_average_position": "",
    "In_account": "",
    "In_plan": "",
    "Searches_Oct_2020": "",
    "Searches_Nov_2020": "",
    "Searches_Dec_2020": "",
    "Searches_Jan_2021": "",
    "Searches_Feb_2021": "",
    "Searches_Mar_2021": "",
    "Searches_Apr_2021": "",
    "Searches_May_2021": "",
    "Searches_Jun_2021": "",
    "Searches_Jul_2021": "",
    "Searches_Aug_2021": "",
    "Searches_Sep_2021": "",
    "Concept_Yang_Lain": "tanaman peneduh",
    "Concept_Tanaman": "",
    "Concept_Merek_Lain": "",
    "Concept_Non_Merek": "Non-Brands"
  },
  {
    "Keyword": "kayu yang bisa buat aquascape",
    "Currency": "IDR",
    "Avg_monthly_searches": 50,
    "Perubahan_persentase_tiga_bulan": "0%",
    "Competition": "Menengah",
    "Competition_indexed_value": 45,
    "Top_of_page_bid_low_range": "",
    "Top_of_page_bid_high_range": "",
    "Ad_impression_share": "",
    "Organic_impression_share": "",
    "Organic_average_position": "",
    "In_account": "",
    "In_plan": "",
    "Searches_Oct_2020": "",
    "Searches_Nov_2020": "",
    "Searches_Dec_2020": "",
    "Searches_Jan_2021": "",
    "Searches_Feb_2021": "",
    "Searches_Mar_2021": "",
    "Searches_Apr_2021": "",
    "Searches_May_2021": "",
    "Searches_Jun_2021": "",
    "Searches_Jul_2021": "",
    "Searches_Aug_2021": "",
    "Searches_Sep_2021": "",
    "Concept_Yang_Lain": "cara",
    "Concept_Tanaman": "",
    "Concept_Merek_Lain": "aquascape",
    "Concept_Non_Merek": ""
  },
  {
    "Keyword": "kayu yang bagus buat aquascape",
    "Currency": "IDR",
    "Avg_monthly_searches": 50,
    "Perubahan_persentase_tiga_bulan": "0%",
    "Competition": "Tinggi",
    "Competition_indexed_value": 100,
    "Top_of_page_bid_low_range": "",
    "Top_of_page_bid_high_range": "",
    "Ad_impression_share": "",
    "Organic_impression_share": "",
    "Organic_average_position": "",
    "In_account": "",
    "In_plan": "",
    "Searches_Oct_2020": "",
    "Searches_Nov_2020": "",
    "Searches_Dec_2020": "",
    "Searches_Jan_2021": "",
    "Searches_Feb_2021": "",
    "Searches_Mar_2021": "",
    "Searches_Apr_2021": "",
    "Searches_May_2021": "",
    "Searches_Jun_2021": "",
    "Searches_Jul_2021": "",
    "Searches_Aug_2021": "",
    "Searches_Sep_2021": "",
    "Concept_Yang_Lain": "",
    "Concept_Tanaman": "",
    "Concept_Merek_Lain": "aquascape",
    "Concept_Non_Merek": ""
  },
  {
    "Keyword": "kayu yang cocok buat aquascape",
    "Currency": "IDR",
    "Avg_monthly_searches": 50,
    "Perubahan_persentase_tiga_bulan": "0%",
    "Competition": "Tinggi",
    "Competition_indexed_value": 100,
    "Top_of_page_bid_low_range": "",
    "Top_of_page_bid_high_range": "",
    "Ad_impression_share": "",
    "Organic_impression_share": "",
    "Organic_average_position": "",
    "In_account": "",
    "In_plan": "",
    "Searches_Oct_2020": "",
    "Searches_Nov_2020": "",
    "Searches_Dec_2020": "",
    "Searches_Jan_2021": "",
    "Searches_Feb_2021": "",
    "Searches_Mar_2021": "",
    "Searches_Apr_2021": "",
    "Searches_May_2021": "",
    "Searches_Jun_2021": "",
    "Searches_Jul_2021": "",
    "Searches_Aug_2021": "",
    "Searches_Sep_2021": "",
    "Concept_Yang_Lain": "",
    "Concept_Tanaman": "",
    "Concept_Merek_Lain": "aquascape",
    "Concept_Non_Merek": ""
  },
  {
    "Keyword": "jenis tumbuhan yang berakar serabut",
    "Currency": "IDR",
    "Avg_monthly_searches": 50,
    "Perubahan_persentase_tiga_bulan": "0%",
    "Competition": "Rendah",
    "Competition_indexed_value": 0,
    "Top_of_page_bid_low_range": "",
    "Top_of_page_bid_high_range": "",
    "Ad_impression_share": "",
    "Organic_impression_share": "",
    "Organic_average_position": "",
    "In_account": "",
    "In_plan": "",
    "Searches_Oct_2020": "",
    "Searches_Nov_2020": "",
    "Searches_Dec_2020": "",
    "Searches_Jan_2021": "",
    "Searches_Feb_2021": "",
    "Searches_Mar_2021": "",
    "Searches_Apr_2021": "",
    "Searches_May_2021": "",
    "Searches_Jun_2021": "",
    "Searches_Jul_2021": "",
    "Searches_Aug_2021": "",
    "Searches_Sep_2021": "",
    "Concept_Yang_Lain": "",
    "Concept_Tanaman": "",
    "Concept_Merek_Lain": "",
    "Concept_Non_Merek": "Non-Brands"
  },
  {
    "Keyword": "cara mengkonsumsi kayu bajakah yang benar",
    "Currency": "IDR",
    "Avg_monthly_searches": 50,
    "Perubahan_persentase_tiga_bulan": "0%",
    "Competition": "Menengah",
    "Competition_indexed_value": 37,
    "Top_of_page_bid_low_range": 562.86,
    "Top_of_page_bid_high_range": 1738.51,
    "Ad_impression_share": "",
    "Organic_impression_share": "",
    "Organic_average_position": "",
    "In_account": "",
    "In_plan": "",
    "Searches_Oct_2020": "",
    "Searches_Nov_2020": "",
    "Searches_Dec_2020": "",
    "Searches_Jan_2021": "",
    "Searches_Feb_2021": "",
    "Searches_Mar_2021": "",
    "Searches_Apr_2021": "",
    "Searches_May_2021": "",
    "Searches_Jun_2021": "",
    "Searches_Jul_2021": "",
    "Searches_Aug_2021": "",
    "Searches_Sep_2021": "",
    "Concept_Yang_Lain": "cara",
    "Concept_Tanaman": "",
    "Concept_Merek_Lain": "",
    "Concept_Non_Merek": "Non-Brands"
  },
  {
    "Keyword": "jaringan tumbuhan yang berfungsi mengangkut air dan garam mineral",
    "Currency": "IDR",
    "Avg_monthly_searches": 50,
    "Perubahan_persentase_tiga_bulan": "∞",
    "Competition": "Rendah",
    "Competition_indexed_value": 0,
    "Top_of_page_bid_low_range": "",
    "Top_of_page_bid_high_range": "",
    "Ad_impression_share": "",
    "Organic_impression_share": "",
    "Organic_average_position": "",
    "In_account": "",
    "In_plan": "",
    "Searches_Oct_2020": "",
    "Searches_Nov_2020": "",
    "Searches_Dec_2020": "",
    "Searches_Jan_2021": "",
    "Searches_Feb_2021": "",
    "Searches_Mar_2021": "",
    "Searches_Apr_2021": "",
    "Searches_May_2021": "",
    "Searches_Jun_2021": "",
    "Searches_Jul_2021": "",
    "Searches_Aug_2021": "",
    "Searches_Sep_2021": "",
    "Concept_Yang_Lain": "air. jaringan",
    "Concept_Tanaman": "daun",
    "Concept_Merek_Lain": "",
    "Concept_Non_Merek": "Non-Brands"
  }
]
